siolib/__init__.py
siolib/exceptions.py
siolib/httphelper.py
siolib/scaleio.py
siolib/utilities.py
siolib-2.0.3.dist-info/DESCRIPTION.rst
siolib-2.0.3.dist-info/METADATA
siolib-2.0.3.dist-info/RECORD
siolib-2.0.3.dist-info/WHEEL
siolib-2.0.3.dist-info/metadata.json
siolib-2.0.3.dist-info/top_level.txt
